{
  "type": "Feature",
  "properties": {
    "gn:admin1_code":"1.0",
    "gn:asciiname":"Goubeto",
    "gn:cc2":"DJ",
    "gn:country_code":"DJ",
    "gn:dem":369,
    "gn:feature_class":"P",
    "gn:feature_code":"PPL",
    "gn:name":"Goub\u00e9to",
    "gn:population":0,
    "gn:timezone":"Africa/Djibouti",
    "iso:country":"DJ",
    "name:und_x_variant":[
        "Goubeto Station",
        "Goub\u00e9to"
    ],
    "wof:name":"Goubeto",
    "wof:placetype":"locality"
},
  "geometry": {"coordinates":[42.98333,11.41667],"type":"Point"}
}