{
  "type": "Feature",
  "properties": {
    "gn:admin1_code":"6.0",
    "gn:asciiname":"`As `Ela",
    "gn:country_code":"DJ",
    "gn:dem":351,
    "gn:feature_class":"P",
    "gn:feature_code":"PPL",
    "gn:name":"\u2018As \u2018\u00cala",
    "gn:population":0,
    "gn:timezone":"Africa/Djibouti",
    "iso:country":"DJ",
    "name:und_x_variant":[
        "Ass\u2019\u00e8yla",
        "Assa-ela",
        "Airoli",
        "\u2018As \u2018\u00cala"
    ],
    "wof:name":"`As `Ela",
    "wof:placetype":"locality"
},
  "geometry": {"coordinates":[42.1025,11.00361],"type":"Point"}
}