{
  "type": "Feature",
  "properties": {
    "gn:admin1_code":"6.0",
    "gn:asciiname":"Yoboki",
    "gn:country_code":"DJ",
    "gn:dem":225,
    "gn:feature_class":"P",
    "gn:feature_code":"PPL",
    "gn:name":"Yoboki",
    "gn:population":0,
    "gn:timezone":"Africa/Djibouti",
    "iso:country":"DJ",
    "name:ara_x_preferred":[
        "\u064a\u0648\u0628\u0648\u0643\u064a"
    ],
    "name:azb_x_preferred":[
        "\u06cc\u0648\u0628\u0648\u06a9\u06cc"
    ],
    "name:ceb_x_preferred":[
        "Yoboki"
    ],
    "name:deu_x_preferred":[
        "Yoboki"
    ],
    "name:est_x_preferred":[
        "Yoboki"
    ],
    "name:fas_x_preferred":[
        "\u06cc\u0648\u0628\u0648\u06a9\u06cc"
    ],
    "name:fra_x_preferred":[
        "Yoboki"
    ],
    "name:ita_x_preferred":[
        "Yoboki"
    ],
    "name:lit_x_preferred":[
        "Jobokis"
    ],
    "name:pol_x_preferred":[
        "Yoboki"
    ],
    "name:rus_x_preferred":[
        "\u0419\u043e\u0431\u043e\u043a\u0438"
    ],
    "name:swe_x_preferred":[
        "Yoboki"
    ],
    "name:tur_x_preferred":[
        "Yoboki"
    ],
    "name:urd_x_preferred":[
        "\u06cc\u0648\u0628\u0648\u06a9\u06cc"
    ],
    "wof:name":"Yoboki",
    "wof:placetype":"locality"
},
  "geometry": {"coordinates":[42.10639000000001,11.51139],"type":"Point"}
}