{
  "type": "Feature",
  "properties": {
    "gn:admin1_code":"6.0",
    "gn:asciiname":"Yoboki",
    "gn:country_code":"DJ",
    "gn:dem":225,
    "gn:feature_class":"P",
    "gn:feature_code":"PPL",
    "gn:name":"Yoboki",
    "gn:population":0,
    "gn:timezone":"Africa/Djibouti",
    "iso:country":"DJ",
    "wof:name":"Yoboki",
    "wof:placetype":"locality"
},
  "geometry": {"coordinates":[42.10639000000001,11.51139],"type":"Point"}
}